<PAMDataset>
  <Metadata>
    <MDI key="DataType">Thematic</MDI>
  </Metadata>
  <Metadata domain="Esri">
    <MDI key="PyramidResamplingType">NEAREST</MDI>
  </Metadata>
  <PAMRasterBand band="1">
    <Histograms>
      <HistItem>
        <HistMin>-0.5</HistMin>
        <HistMax>95.5</HistMax>
        <BucketCount>96</BucketCount>
        <IncludeOutOfRange>1</IncludeOutOfRange>
        <Approximate>0</Approximate>
        <HistCounts>0|0|0|0|0|0|0|0|0|0|0|750623|0|0|0|0|0|0|0|0|0|3907598|2704590|1152929|537742|0|0|0|0|0|0|90006|0|0|0|0|0|0|0|0|0|11030912|7292929|3143149|0|0|0|0|0|0|0|0|1035223|0|0|0|0|0|0|0|0|0|0|0|0|0|0|0|0|0|0|1362438|0|0|0|0|0|0|0|0|0|5756550|127380|0|0|0|0|0|0|0|1133693|0|0|0|0|74859</HistCounts>
      </HistItem>
    </Histograms>
    <Metadata>
      <MDI key="RepresentationType">THEMATIC</MDI>
      <MDI key="STATISTICS_COVARIANCES">416.413342682523</MDI>
      <MDI key="STATISTICS_EXCLUDEDVALUES"></MDI>
      <MDI key="STATISTICS_MAXIMUM">95</MDI>
      <MDI key="STATISTICS_MEAN">45.440467069072</MDI>
      <MDI key="STATISTICS_MEDIAN">41.000000</MDI>
      <MDI key="STATISTICS_MINIMUM">11</MDI>
      <MDI key="STATISTICS_SKIPFACTORX">1</MDI>
      <MDI key="STATISTICS_SKIPFACTORY">1</MDI>
      <MDI key="STATISTICS_STDDEV">20.406208434751</MDI>
    </Metadata>
  </PAMRasterBand>
</PAMDataset>
